treeringanalyzer/__init__.py
treeringanalyzer/analyzer.py
treeringanalyzer/cli.py
treeringanalyzer/config.py
treeringanalyzer/main.py
treeringanalyzer/analysis/__init__.py
treeringanalyzer/analysis/chain_analysis_tools.py
treeringanalyzer/analysis/chain_neighbourhood.py
treeringanalyzer/analysis/chain_system_manager.py
treeringanalyzer/analysis/chains_bag.py
treeringanalyzer/analysis/connect_chains.py
treeringanalyzer/analysis/connect_parameters.py
treeringanalyzer/analysis/interpolation_nodes.py
treeringanalyzer/detection/__init__.py
treeringanalyzer/detection/canny_devernay_edge_detector.py
treeringanalyzer/detection/filter_edges.py
treeringanalyzer/externals/devernay_1.0/devernay.out
treeringanalyzer/geometry/__init__.py
treeringanalyzer/geometry/angular_set.py
treeringanalyzer/geometry/chain.py
treeringanalyzer/geometry/curve.py
treeringanalyzer/geometry/geometry_utils.py
treeringanalyzer/geometry/node.py
treeringanalyzer/geometry/ray.py
treeringanalyzer/geometry/ring.py
treeringanalyzer/geometry/virtual_band_generator.py
treeringanalyzer/processing/__init__.py
treeringanalyzer/processing/chain_context.py
treeringanalyzer/processing/postprocessing.py
treeringanalyzer/processing/preprocessing.py
treeringanalyzer/processing/sampling.py
treeringanalyzer/utils/__init__.py
treeringanalyzer/utils/file_utils.py
treeringanalyzer/utils/results_handler.py
treeringanalyzer/visualization/__init__.py
treeringanalyzer/visualization/color.py
treeringanalyzer/visualization/drawing.py
tree_ring_analyzer-0.3.0.dist-info/METADATA
tree_ring_analyzer-0.3.0.dist-info/WHEEL
tree_ring_analyzer-0.3.0.dist-info/entry_points.txt
tree_ring_analyzer-0.3.0.dist-info/top_level.txt
tree_ring_analyzer-0.3.0.dist-info/RECORD
